{
    "name": "Global Information",
    "numberOfRequests": {
        "total": 18269,
        "ok": 18269,
        "ko": 0
    },
    "minResponseTime": {
        "total": 15,
        "ok": 15,
        "ko": 0
    },
    "maxResponseTime": {
        "total": 979,
        "ok": 979,
        "ko": 0
    },
    "meanResponseTime": {
        "total": 27,
        "ok": 27,
        "ko": 0
    },
    "standardDeviation": {
        "total": 20,
        "ok": 20,
        "ko": 0
    },
    "percentiles1": {
        "total": 25,
        "ok": 25,
        "ko": 0
    },
    "percentiles2": {
        "total": 29,
        "ok": 29,
        "ko": 0
    },
    "percentiles3": {
        "total": 35,
        "ok": 35,
        "ko": 0
    },
    "percentiles4": {
        "total": 48,
        "ok": 48,
        "ko": 0
    },
    "group1": {
    "name": "t < 800 ms",
    "count": 18267,
    "percentage": 100
},
    "group2": {
    "name": "800 ms < t < 1200 ms",
    "count": 2,
    "percentage": 0
},
    "group3": {
    "name": "t > 1200 ms",
    "count": 0,
    "percentage": 0
},
    "group4": {
    "name": "failed",
    "count": 0,
    "percentage": 0
},
    "meanNumberOfRequestsPerSecond": {
        "total": 50.18956043956044,
        "ok": 50.18956043956044,
        "ko": 0
    }
}